deepagents_backends/__init__.py
deepagents_backends-0.1.1.dist-info/licenses/LICENSE
deepagents_backends-0.1.1.dist-info/METADATA
deepagents_backends-0.1.1.dist-info/WHEEL
deepagents_backends-0.1.1.dist-info/top_level.txt
deepagents_backends-0.1.1.dist-info/RECORD
