Metadata-Version: 2.4
Name: deepagents-backends
Version: 0.1.1
Summary: S3 and PostgreSQL remote backends for LangChain Deep Agents
Requires-Python: >=3.12
License-File: LICENSE
Requires-Dist: aioboto3>=15.5.0
Requires-Dist: deepagents>=0.3.1
Requires-Dist: psycopg[binary,pool]>=3.3.2
Requires-Dist: wcmatch>=10.1
Dynamic: license-file
